lucid_H/EmailServices.py
lucid_H/__init__.py
lucid_H-1.1.5.dist-info/LICENCE.txt
lucid_H-1.1.5.dist-info/METADATA
lucid_H-1.1.5.dist-info/WHEEL
lucid_H-1.1.5.dist-info/top_level.txt
lucid_H-1.1.5.dist-info/RECORD
