Metadata-Version: 2.1
Name: lucid-H
Version: 1.1.5
Summary: WORK_ENV emails
Author: HemantDhanwar
Author-email: <ashuhemantsingh@gmail.com>
License: UNKNOWN
Keywords: python,Email,directory size,dir size
Platform: UNKNOWN
Classifier: Development Status :: 1 - Planning
Classifier: Intended Audience :: Developers
Classifier: Programming Language :: Python :: 3
Classifier: Operating System :: Unix
Classifier: Operating System :: MacOS :: MacOS X
Classifier: Operating System :: Microsoft :: Windows
License-File: LICENCE.txt
Requires-Dist: smtpemail
Requires-Dist: fsspec
Requires-Dist: getpass4
Requires-Dist: pandas
Requires-Dist: numpy
Requires-Dist: gitpython
Requires-Dist: shutil
